.travis.yml
CHANGES.txt
COPYRIGHT.txt
LICENSE.txt
MANIFEST.in
Makefile
README.txt
bootstrap.py
buildout.cfg
setup.py
src/cipher/__init__.py
src/cipher.longrequest.egg-info/PKG-INFO
src/cipher.longrequest.egg-info/SOURCES.txt
src/cipher.longrequest.egg-info/dependency_links.txt
src/cipher.longrequest.egg-info/entry_points.txt
src/cipher.longrequest.egg-info/not-zip-safe
src/cipher.longrequest.egg-info/pbr.json
src/cipher.longrequest.egg-info/requires.txt
src/cipher.longrequest.egg-info/top_level.txt
src/cipher/longrequest/__init__.py
src/cipher/longrequest/interfaces.py
src/cipher/longrequest/longrequest.py
src/cipher/longrequest/subscribers.zcml
src/cipher/longrequest/tests.py
src/cipher/longrequest/zope_subscribers.zcml
src/cipher/longrequest/testing/paster.ini