Metadata-Version: 1.1
Name: cipher.longrequest
Version: 1.0.10
Summary: Detecting long requests LIVE, using paster
Home-page: http://pypi.python.org/pypi/cipher.longrequest/
Author: Zope Foundation and Contributors
Author-email: zope-dev@zope.org
License: ZPL 2.1
Keywords: CipherHealth long request thread paster
Platform: UNKNOWN
Classifier: Development Status :: 4 - Beta
Classifier: Environment :: Web Environment
Classifier: Intended Audience :: Developers
Classifier: Programming Language :: Python
Classifier: Natural Language :: English
Classifier: Operating System :: OS Independent
Classifier: Topic :: Internet :: WWW/HTTP
Classifier: Framework :: Zope3
